xy/Horizontal.py
xy/__init__.py
xy/base.py
xy/run.py
vr.xy-0.0.5.dist-info/LICENSE
vr.xy-0.0.5.dist-info/METADATA
vr.xy-0.0.5.dist-info/WHEEL
vr.xy-0.0.5.dist-info/entry_points.txt
vr.xy-0.0.5.dist-info/top_level.txt
vr.xy-0.0.5.dist-info/zip-safe
vr.xy-0.0.5.dist-info/RECORD
