Metadata-Version: 2.1
Name: vr.xy
Version: 0.0.5
Summary: (x, y) for pr to make vr video based on Python3
Home-page: https://gitee.com/Mr_52Hz/vxy.git
Author: mr52hz
Author-email: mr52hz@qq.com
License: MIT
Keywords: python3 vr.xy terminal
Platform: UNKNOWN
Classifier: Programming Language :: Python :: 3
Classifier: License :: OSI Approved :: MIT License
Classifier: Operating System :: OS Independent
Requires-Python: >=3.0
License-File: LICENSE
